Products
README.txt
setup.py
Products/__init__.py
Products.PloneContentTemplates.egg-info/PKG-INFO
Products.PloneContentTemplates.egg-info/SOURCES.txt
Products.PloneContentTemplates.egg-info/dependency_links.txt
Products.PloneContentTemplates.egg-info/entry_points.txt
Products.PloneContentTemplates.egg-info/namespace_packages.txt
Products.PloneContentTemplates.egg-info/not-zip-safe
Products.PloneContentTemplates.egg-info/requires.txt
Products.PloneContentTemplates.egg-info/top_level.txt
Products/PloneContentTemplates/__init__.py
Products/PloneContentTemplates/changes.txt
Products/PloneContentTemplates/config.py
Products/PloneContentTemplates/configure.zcml
Products/PloneContentTemplates/license.txt
Products/PloneContentTemplates/readme.txt
Products/PloneContentTemplates/version.txt
Products/PloneContentTemplates/Extensions/DEPRECATED.txt
Products/PloneContentTemplates/Extensions/Install.py
Products/PloneContentTemplates/_darcs/index_invalid
Products/PloneContentTemplates/_darcs/inventory
Products/PloneContentTemplates/_darcs/tentative_pristine
Products/PloneContentTemplates/_darcs/patches/20071105103942-422b6-7d2b0d670ec09a98f154a05b9fed5cc2553135be.gz
Products/PloneContentTemplates/_darcs/patches/20071105104143-422b6-c583984b90036f7d02070fcd9110b37a5d186478.gz
Products/PloneContentTemplates/_darcs/patches/20071105104658-422b6-a1b6c3b1c1753c9ceb1ab354c647a6e7909c66d1.gz
Products/PloneContentTemplates/_darcs/patches/20071105111139-422b6-a68800e2d18fe5b1dab3639243582ba9776d026b.gz
Products/PloneContentTemplates/_darcs/patches/20071105194721-422b6-76feebb685f88d1d217716565c1e14b316a1fc28.gz
Products/PloneContentTemplates/_darcs/patches/20071105203407-422b6-53f7f9c300a8f220b1f646e95996aba709daee73.gz
Products/PloneContentTemplates/_darcs/patches/20071201124940-422b6-7be88dcf18a6690a3fb9fdb7045b9dd8979b9fcd.gz
Products/PloneContentTemplates/_darcs/patches/20120119132510-422b6-d497bb36df927e78f2a82a4874cfe72c37ec961c.gz
Products/PloneContentTemplates/_darcs/patches/pending
Products/PloneContentTemplates/_darcs/patches/pending.tentative
Products/PloneContentTemplates/_darcs/prefs/author
Products/PloneContentTemplates/_darcs/prefs/binaries
Products/PloneContentTemplates/_darcs/prefs/boring
Products/PloneContentTemplates/_darcs/prefs/defaultrepo
Products/PloneContentTemplates/_darcs/prefs/motd
Products/PloneContentTemplates/_darcs/prefs/repos
Products/PloneContentTemplates/_darcs/pristine/__init__.py
