Metadata-Version: 1.0
Name: Products.PloneContentTemplates
Version: 1.2
Summary: Enables creating content based on (archetypes-based and editable) content templates
Home-page: http://www.nidelven-it.no/d
Author: Morten W. Petersen
Author-email: info@nidelven-it.no
License: GPL
Keywords: python plone archetypes content templates plone2 plone3 plone4
Platform: UNKNOWN
Classifier: Programming Language :: Python
Classifier: Development Status :: 5 - Production/Stable
Classifier: Framework :: Plone
Classifier: License :: OSI Approved :: GNU General Public License (GPL)
